TradeMaster/TradeSync.py
TradeMaster/Websocket.py
TradeMaster/__init__.py
TradeMaster/base_validation/__init__.py
TradeMaster/base_validation/_orderValidation.py
TradeMaster/base_validation/checksum.py
TradeMaster/base_validation/file_read.py
TradeMaster/base_validation/timestamp.py
TradeMaster/network/__init__.py
TradeMaster/network/api_client.py
TradeMaster/network/device_identifier.py
config/__init__.py
config/config.py
config/settings.py
utility/__init__.py
utility/library.py
a3_tradehub_test_2-1.1.2.dist-info/METADATA
a3_tradehub_test_2-1.1.2.dist-info/WHEEL
a3_tradehub_test_2-1.1.2.dist-info/top_level.txt
a3_tradehub_test_2-1.1.2.dist-info/RECORD
