Metadata-Version: 2.4
Name: a3_tradehub_test_2
Version: 1.1.2
Summary: Python SDK for integrating with Aliceblue trading platform.
Home-page: https://a3.aliceblueonline.com/
Author: Codifi
Author-email: periyasamy@codifi.in
License: MIT
Project-URL: Documentation, https://ant.aliceblueonline.com/productdocumentation/
Classifier: Programming Language :: Python :: 3.8
Classifier: License :: OSI Approved :: MIT License
Classifier: Operating System :: OS Independent
Classifier: Natural Language :: English
Classifier: Intended Audience :: Developers
Requires-Python: >=3.7
Requires-Dist: requests
Requires-Dist: pandas
Requires-Dist: websocket-client
Requires-Dist: rel
Dynamic: author
Dynamic: author-email
Dynamic: classifier
Dynamic: description
Dynamic: description-content-type
Dynamic: home-page
Dynamic: license
Dynamic: project-url
Dynamic: requires-dist
Dynamic: requires-python
Dynamic: summary
